ZetcodeNetJiaochengChuyi/README.md
ZetcodeNetJiaochengChuyi/__init__.py
ZetcodeNetJiaochengChuyi/__main__.py
ZetcodeNetJiaochengChuyi/file.epub
ZetcodeNetJiaochengChuyi/index.html
ZetcodeNetJiaochengChuyi/css/__init__.py
ZetcodeNetJiaochengChuyi/css/annotations.css
ZetcodeNetJiaochengChuyi/css/main.css
ZetcodeNetJiaochengChuyi/css/normalize.css
ZetcodeNetJiaochengChuyi/css/popup.css
ZetcodeNetJiaochengChuyi/font/__init__.py
ZetcodeNetJiaochengChuyi/font/fontello.eot
ZetcodeNetJiaochengChuyi/font/fontello.svg
ZetcodeNetJiaochengChuyi/font/fontello.ttf
ZetcodeNetJiaochengChuyi/font/fontello.woff
ZetcodeNetJiaochengChuyi/img/__init__.py
ZetcodeNetJiaochengChuyi/img/annotator-glyph-sprite.png
ZetcodeNetJiaochengChuyi/img/annotator-icon-sprite.png
ZetcodeNetJiaochengChuyi/img/apple-touch-icon.png
ZetcodeNetJiaochengChuyi/img/cancelfullscreen.png
ZetcodeNetJiaochengChuyi/img/close.png
ZetcodeNetJiaochengChuyi/img/fullscreen.png
ZetcodeNetJiaochengChuyi/img/loader.gif
ZetcodeNetJiaochengChuyi/img/menu-icon.png
ZetcodeNetJiaochengChuyi/img/save.png
ZetcodeNetJiaochengChuyi/img/saved.png
ZetcodeNetJiaochengChuyi/img/settings-s.png
ZetcodeNetJiaochengChuyi/img/settings.png
ZetcodeNetJiaochengChuyi/img/star.png
ZetcodeNetJiaochengChuyi/js/__init__.py
ZetcodeNetJiaochengChuyi/js/epub.js
ZetcodeNetJiaochengChuyi/js/epub.min.js
ZetcodeNetJiaochengChuyi/js/epub.min.map
ZetcodeNetJiaochengChuyi/js/hooks.min.js
ZetcodeNetJiaochengChuyi/js/hooks.min.map
ZetcodeNetJiaochengChuyi/js/reader.js
ZetcodeNetJiaochengChuyi/js/reader.js.map
ZetcodeNetJiaochengChuyi/js/reader.min.js
ZetcodeNetJiaochengChuyi/js/reader.min.map
ZetcodeNetJiaochengChuyi/js/hooks/__init__.py
ZetcodeNetJiaochengChuyi/js/hooks/extensions/__init__.py
ZetcodeNetJiaochengChuyi/js/hooks/extensions/highlight.js
ZetcodeNetJiaochengChuyi/js/libs/__init__.py
ZetcodeNetJiaochengChuyi/js/libs/jquery.min.js
ZetcodeNetJiaochengChuyi/js/libs/localforage.min.js
ZetcodeNetJiaochengChuyi/js/libs/screenfull.js
zetcode_net_jiaocheng_chuyi-2024.3.5.0.dist-info/METADATA
zetcode_net_jiaocheng_chuyi-2024.3.5.0.dist-info/WHEEL
zetcode_net_jiaocheng_chuyi-2024.3.5.0.dist-info/entry_points.txt
zetcode_net_jiaocheng_chuyi-2024.3.5.0.dist-info/top_level.txt
zetcode_net_jiaocheng_chuyi-2024.3.5.0.dist-info/RECORD
